fast_serializer.cpython-311-darwin.so
fast_serializer/__init__.cpython-311-darwin.so
fast_serializer/__init__.py
fast_serializer/automation.cpython-311-darwin.so
fast_serializer/automation.py
fast_serializer/constants.cpython-311-darwin.so
fast_serializer/constants.py
fast_serializer/dataclass_config.cpython-311-darwin.so
fast_serializer/dataclass_config.py
fast_serializer/decorators.cpython-311-darwin.so
fast_serializer/decorators.py
fast_serializer/exceptions.cpython-311-darwin.so
fast_serializer/exceptions.py
fast_serializer/fast_dataclass.cpython-311-darwin.so
fast_serializer/fast_dataclass.py
fast_serializer/field.cpython-311-darwin.so
fast_serializer/field.py
fast_serializer/field.pyi
fast_serializer/globals.cpython-311-darwin.so
fast_serializer/globals.py
fast_serializer/json_schema.cpython-311-darwin.so
fast_serializer/json_schema.py
fast_serializer/serializer.cpython-311-darwin.so
fast_serializer/serializer.py
fast_serializer/type_parser.cpython-311-darwin.so
fast_serializer/type_parser.py
fast_serializer/types.cpython-311-darwin.so
fast_serializer/types.py
fast_serializer/utils.cpython-311-darwin.so
fast_serializer/utils.py
fast_serializer/validator.cpython-311-darwin.so
fast_serializer/validator.py
fast_serializer-0.8.4.dist-info/LICENSE
fast_serializer-0.8.4.dist-info/METADATA
fast_serializer-0.8.4.dist-info/WHEEL
fast_serializer-0.8.4.dist-info/top_level.txt
fast_serializer-0.8.4.dist-info/RECORD
