Metadata-Version: 2.1
Name: fast-serializer
Version: 0.8.4
Summary: python 数据类验证器和序列化框架
Home-page: https://github.com/breezechime/fast-serializer
Author: 且听风铃、我是指针*、ZDLAY、KYZ
Author-email: breezechime@163.com
License: MIT
Classifier: License :: OSI Approved :: MIT License
Classifier: Operating System :: OS Independent
Classifier: Programming Language :: Python :: 3
Requires-Python: >=3.6
License-File: LICENSE
